pdsparser/_PDS3_GRAMMAR.py
pdsparser/__init__.py
pdsparser/_fast_dict.py
pdsparser/_version.py
pdsparser/utils.py
rms_pdsparser-2.0.0.dist-info/licenses/LICENSE
rms_pdsparser-2.0.0.dist-info/METADATA
rms_pdsparser-2.0.0.dist-info/WHEEL
rms_pdsparser-2.0.0.dist-info/top_level.txt
rms_pdsparser-2.0.0.dist-info/RECORD
