Metadata-Version: 2.4
Name: rms-pdsparser
Version: 2.0.0
Summary: Routines for parsing PDS3 labels
Maintainer-email: "Robert S. French" <rfrench@seti.org>
License: Apache-2.0
Project-URL: Homepage, https://github.com/SETI/rms-pdsparser
Project-URL: Repository, https://github.com/SETI/rms-pdsparser
Project-URL: Source, https://github.com/SETI/rms-pdsparser
Project-URL: Issues, https://github.com/SETI/rms-pdsparser/issues
Keywords: NASA,PDS3
Classifier: Development Status :: 5 - Production/Stable
Classifier: Natural Language :: English
Classifier: Topic :: Scientific/Engineering
Classifier: Topic :: Scientific/Engineering :: Astronomy
Classifier: Topic :: Software Development :: Libraries :: Python Modules
Classifier: Topic :: Utilities
Classifier: License :: OSI Approved :: Apache Software License
Classifier: Programming Language :: Python :: 3.9
Classifier: Programming Language :: Python :: 3.10
Classifier: Programming Language :: Python :: 3.11
Classifier: Programming Language :: Python :: 3.12
Classifier: Programming Language :: Python :: 3.13
Classifier: Operating System :: MacOS :: MacOS X
Classifier: Operating System :: POSIX :: Linux
Classifier: Operating System :: Microsoft :: Windows
Requires-Python: >=3.9
License-File: LICENSE
Requires-Dist: pyparsing
Requires-Dist: rms-filecache
Requires-Dist: rms-julian
Dynamic: license-file
